[{"month":"2008-10-01","star":2.0},{"month":"2011-03-01","star":3.0},{"month":"2012-01-01","star":4.0},{"month":"2012-10-01","star":3.0},{"month":"2013-10-01","star":4.0},{"month":"2013-11-01","star":4.0},{"month":"2014-05-01","star":4.0},{"month":"2014-10-01","star":4.0},{"month":"2014-11-01","star":4.0},{"month":"2015-01-01","star":5.0},{"month":"2015-10-01","star":4.0},{"month":"2015-11-01","star":4.0},{"month":"2016-08-01","star":4.0},{"month":"2016-10-01","star":3.5},{"month":"2017-10-01","star":5.0},{"month":"2018-10-01","star":4.0},{"month":"2019-10-01","star":4.0}]